LICENSE.txt
MANIFEST.in
README.rst
setup.py
tox.ini
django_sitemapper.egg-info/PKG-INFO
django_sitemapper.egg-info/SOURCES.txt
django_sitemapper.egg-info/dependency_links.txt
django_sitemapper.egg-info/not-zip-safe
django_sitemapper.egg-info/requires.txt
django_sitemapper.egg-info/top_level.txt
docs/Makefile
docs/api.rst
docs/conf.py
docs/db.sqlite3
docs/index.rst
docs/install.rst
docs/make.bat
docs/requirements.txt
docs/settings.pyc
docs/sitemaps.rst
example/__init__.py
example/manage.py
example/settings.py
example/urls.py
example/wsgi.py
example/demoapp/__init__.py
example/demoapp/admin.py
example/demoapp/models.py
example/demoapp/sitemaps.py
example/demoapp/urls.py
example/demoapp/migrations/0001_initial.py
example/demoapp/migrations/__init__.py
example/demoapp/south_migrations/0001_initial.py
example/demoapp/south_migrations/__init__.py
example/demoapp/templates/demoapp/demo_detail.html
sitemapper/__init__.py
sitemapper/admin.py
sitemapper/mixins.py
sitemapper/models.py
sitemapper/sitemaps.py
sitemapper/migrations/0001_initial.py
sitemapper/migrations/0002_auto_20141007_0329.py
sitemapper/migrations/__init__.py
sitemapper/south_migrations/0001_initial.py
sitemapper/south_migrations/0002_auto__chg_field_sitemapentry_priority__chg_field_sitemapentry_changefr.py
sitemapper/south_migrations/__init__.py
sitemapper/tests/__init__.py
sitemapper/tests/models.py
sitemapper/tests/run.py
sitemapper/tests/test_sitemap.py
sitemapper/tests/urls.py
sitemapper/tests/fixtures/test.json