Metadata-Version: 1.1
Name: django-sitemapper
Version: 1.0.0
Summary: A small Django app to manage sitemap.xml overrides on a per-object basis
Home-page: https://bitbucket.org/mhurt/django-sitemapper/
Author: Mike Hurt
Author-email: mike@mhtechnical.net
License: MIT License
Keywords: python django sitemap.xml
Platform: UNKNOWN
Classifier: Development Status :: 5 - Production/Stable
Classifier: Environment :: Web Environment
Classifier: Framework :: Django
Classifier: Intended Audience :: Developers
Classifier: License :: OSI Approved :: MIT License
Classifier: Operating System :: OS Independent
Classifier: Programming Language :: Python
Classifier: Programming Language :: Python :: 2.7
Classifier: Programming Language :: Python :: 3
Classifier: Topic :: Internet :: WWW/HTTP
Classifier: Topic :: Internet :: WWW/HTTP :: Dynamic Content
